blitzer/__init__.py
blitzer/blitzer.py
blitzer-0.1.dist-info/LICENSE
blitzer-0.1.dist-info/WHEEL
blitzer-0.1.dist-info/METADATA
blitzer-0.1.dist-info/RECORD
