Metadata-Version: 2.1
Name: blitzer
Version: 0.1
Summary: Simple Python Timing Library
Author-email: Christoph Kattmann <christoph.kattmann@gmail.com>
Classifier: License :: OSI Approved :: MIT License
Project-URL: Home, https://github.com/ckattmann/blitzer
